LICENSE
MANIFEST.in
README.md
setup.cfg
setup.py
clevertimapi/__init__.py
clevertimapi/case.py
clevertimapi/comment.py
clevertimapi/company.py
clevertimapi/compat.py
clevertimapi/contact.py
clevertimapi/customfield.py
clevertimapi/endpoint.py
clevertimapi/file.py
clevertimapi/note.py
clevertimapi/opportunity.py
clevertimapi/session.py
clevertimapi/task.py
clevertimapi/user.py
clevertimapi/utils.py
clevertimapi.egg-info/PKG-INFO
clevertimapi.egg-info/SOURCES.txt
clevertimapi.egg-info/dependency_links.txt
clevertimapi.egg-info/requires.txt
clevertimapi.egg-info/top_level.txt
tests/__init__.py
tests/mock_utils.py
tests/test_case.py
tests/test_company.py
tests/test_contact.py
tests/test_customfield.py
tests/test_endpoint.py
tests/test_file.py
tests/test_note.py
tests/test_opportunity.py
tests/test_session.py
tests/test_task.py
tests/test_user.py
tests/test_utils.py