Metadata-Version: 1.1
Name: clevertimapi
Version: 0.0.1
Summary: Clevertim CRM Python API
Home-page: https://github.com/ciprianmiclaus/clevertim-api-py
Author: Ciprian Miclaus
Author-email: ciprianm@gmail.com
License: BSD3
Keywords: Clevertim CRM contact management API development
Platform: UNKNOWN
Classifier: Development Status :: 4 - Beta
Classifier: Intended Audience :: Developers
Classifier: Topic :: Software Development :: Libraries
Classifier: Programming Language :: Python :: 2
Classifier: Programming Language :: Python :: 2.6
Classifier: Programming Language :: Python :: 2.7
Classifier: Programming Language :: Python :: 3
Classifier: Programming Language :: Python :: 3.2
Classifier: Programming Language :: Python :: 3.3
Classifier: Programming Language :: Python :: 3.4
Classifier: Programming Language :: Python :: 3.5
Classifier: Programming Language :: Python :: 3.6
